funclp/__init__.py
funclp/distributions/BinomialDistribution.py
funclp/distributions/GammaDistribution.py
funclp/distributions/GaussianDistribution.py
funclp/distributions/PoissonDistribution.py
funclp/distributions/__init__.py
funclp/estimators/LSE.py
funclp/estimators/MLE.py
funclp/estimators/__init__.py
funclp/fits/LM.py
funclp/fits/__init__.py
funclp/functions/__init__.py
funclp/functions/_template_function.py
funclp/functions/_template_tools.py
funclp/functions/airys/Airy.py
funclp/functions/airys/Airy2D.py
funclp/functions/airys/__init__.py
funclp/functions/airys/_airys.py
funclp/functions/exponentials/Exponential1.py
funclp/functions/exponentials/Exponential2.py
funclp/functions/exponentials/Exponential3.py
funclp/functions/exponentials/__init__.py
funclp/functions/exponentials/_exponentials.py
funclp/functions/gaussians/Gaussian.py
funclp/functions/gaussians/Gaussian2D.py
funclp/functions/gaussians/GaussianBeam.py
funclp/functions/gaussians/IsoGaussian.py
funclp/functions/gaussians/__init__.py
funclp/functions/gaussians/_gaussians.py
funclp/functions/masks/Diamond.py
funclp/functions/masks/Disc.py
funclp/functions/masks/Rectangle.py
funclp/functions/masks/__init__.py
funclp/functions/masks/_masks.py
funclp/functions/polynomials/Polynomial1.py
funclp/functions/polynomials/Polynomial2.py
funclp/functions/polynomials/Polynomial3.py
funclp/functions/polynomials/Polynomial4.py
funclp/functions/polynomials/Polynomial5.py
funclp/functions/polynomials/__init__.py
funclp/modules/CudaReference_LP/CudaReference.py
funclp/modules/CudaReference_LP/__init__.py
funclp/modules/CudaReference_LP/functions/__init__.py
funclp/modules/CudaReference_LP/functions/__template__.py
funclp/modules/CudaReference_LP/test_CudaReference.py
funclp/modules/Distribution_LP/Distribution.py
funclp/modules/Distribution_LP/__init__.py
funclp/modules/Distribution_LP/functions/__init__.py
funclp/modules/Distribution_LP/functions/__template__.py
funclp/modules/Distribution_LP/test_Distribution.py
funclp-0.1.8.dist-info/WHEEL
funclp-0.1.8.dist-info/METADATA
funclp-0.1.8.dist-info/RECORD
