Metadata-Version: 2.3
Name: funclp
Version: 0.1.8
Summary: A library for defining mathematical functions and fits.
Requires-Dist: corelp
Requires-Dist: numba
Requires-Dist: numpy
Requires-Dist: plotlp
Requires-Dist: cupy-cuda11x ; extra == 'cuda11'
Requires-Dist: numba-cuda ; extra == 'cuda11'
Requires-Dist: cupy-cuda12x ; extra == 'cuda12'
Requires-Dist: numba-cuda ; extra == 'cuda12'
Requires-Dist: cupy-cuda13x ; extra == 'cuda13'
Requires-Dist: numba-cuda ; extra == 'cuda13'
Requires-Python: >=3.12
Provides-Extra: cuda11
Provides-Extra: cuda12
Provides-Extra: cuda13
